Old_VirStrain_112/S0_remove_complete_same.py
Old_VirStrain_112/S1_extract_kmer.py
Old_VirStrain_112/S2.5_Split_cls_hierarchical.py
Old_VirStrain_112/S2.5_Split_cls_hierarchical_beifen.py
Old_VirStrain_112/S2.5_Split_cls_hierarchical_with_perl.py
Old_VirStrain_112/S2_remove_redundant_For_Me.py
Old_VirStrain_112/S3_Strain_pred_My_Method_For_HIV.py
Old_VirStrain_112/S3_Strain_pred_My_Method_V0819_Val.py
Old_VirStrain_112/S3_Strain_pred_My_Method_V0819_Val_beifen.py
Old_VirStrain_112/S3_Strain_pred_My_Method_V0819_Val_median.py
Old_VirStrain_112/S4_Plot_strain_cov.py
Old_VirStrain_112/S4_Plot_strain_cov_beifen.py
Old_VirStrain_112/VirStrain.py
Old_VirStrain_112/VirStrain_build.py
Old_VirStrain_112/__init__.py
Old_VirStrain_112/aln2cluster-withMC-noDash-hiv.py
Old_VirStrain_112/anno_all_cls_for_pipe.py
VirStrain/S0_remove_complete_same.py
VirStrain/S1_extract_kmer.py
VirStrain/S2.5_Split_cls_hierarchical.py
VirStrain/S2.5_Split_cls_hierarchical_beifen.py
VirStrain/S2.5_Split_cls_hierarchical_with_perl.py
VirStrain/S2_remove_redundant_For_Me.py
VirStrain/S3_Strain_pred_My_Method_For_HIV.py
VirStrain/S3_Strain_pred_My_Method_V0819_Val.py
VirStrain/S3_Strain_pred_My_Method_V0819_Val_beifen.py
VirStrain/S3_Strain_pred_My_Method_V0819_Val_contig.py
VirStrain/S3_Strain_pred_My_Method_V0819_Val_median.py
VirStrain/S4_Plot_strain_cov.py
VirStrain/S4_Plot_strain_cov_beifen.py
VirStrain/VirStrain.py
VirStrain/VirStrain_build.py
VirStrain/VirStrain_contig.py
VirStrain/VirStrain_contigDB_merge.py
VirStrain/__init__.py
VirStrain/aln2cluster-overlap-kmer-withd.pl
VirStrain/aln2cluster-overlap-kmer.pl
VirStrain/aln2cluster-withMC-noDash-hiv.py
VirStrain/aln2entropy.pl
VirStrain/anno_all_cls_for_pipe.py
VirStrain/jellyfish-linux
VirStrain_112/S0_remove_complete_same.py
VirStrain_112/S1_extract_kmer.py
VirStrain_112/S2.5_Split_cls_hierarchical.py
VirStrain_112/S2.5_Split_cls_hierarchical_beifen.py
VirStrain_112/S2.5_Split_cls_hierarchical_with_perl.py
virstrain-1.17.dist-info/LICENSE.txt
virstrain-1.17.dist-info/METADATA
virstrain-1.17.dist-info/WHEEL
virstrain-1.17.dist-info/entry_points.txt
virstrain-1.17.dist-info/top_level.txt
virstrain-1.17.dist-info/zip-safe
virstrain-1.17.dist-info/RECORD
