Metadata-Version: 2.1
Name: virstrain
Version: 1.17
Summary: An RNA/DNA virus strain-level identification tool for short reads.
Home-page: https://github.com/liaoherui/VirStrain
Author: Liao Herui
Author-email: heruiliao2-c@my.cityu.edu.hk
License: UNKNOWN
Platform: UNKNOWN
Classifier: Programming Language :: Python :: 3
License-File: LICENSE.txt
Requires-Dist: networkx (==2.4)
Requires-Dist: numpy (==1.17.3)
Requires-Dist: pandas (==1.0.1)
Requires-Dist: biopython (==1.74)
Requires-Dist: plotly (==3.10.0)
Requires-Dist: matplotlib (==3.1.2)
